{
    "imgHeight": 1080,
    "imgWidth": 1920,
    "objects": [
        {
            "label": "building",
            "polygon": [
                [
                    6,
                    290
                ],
                [
                    870,
                    280
                ],
                [
                    1916,
                    328
                ],
                [
                    1916,
                    245
                ],
                [
                    0,
                    240
                ]
            ]
        },
        {
            "label": "car",
            "polygon": [
                [
                    229,
                    257
                ],
                [
                    232,
                    298
                ],
                [
                    502,
                    298
                ],
                [
                    506,
                    286
                ],
                [
                    523,
                    288
                ],
                [
                    521,
                    298
                ],
                [
                    599,
                    290
                ],
                [
                    637,
                    273
                ],
                [
                    629,
                    239
                ],
                [
                    231,
                    241
                ]
            ]
        },
        {
            "label": "motorcycble",
            "polygon": [
                [
                    848,
                    283
                ],
                [
                    859,
                    288
                ],
                [
                    863,
                    284
                ],
                [
                    871,
                    283
                ],
                [
                    876,
                    286
                ],
                [
                    879,
                    290
                ],
                [
                    889,
                    290
                ],
                [
                    891,
                    286
                ],
                [
                    898,
                    281
                ],
                [
                    904,
                    279
                ],
                [
                    910,
                    282
                ],
                [
                    917,
                    286
                ],
                [
                    926,
                    288
                ],
                [
                    931,
                    286
                ],
                [
                    929,
                    279
                ],
                [
                    932,
                    272
                ],
                [
                    935,
                    253
                ],
                [
                    917,
                    252
                ],
                [
                    912,
                    268
                ],
                [
                    915,
                    284
                ],
                [
                    894,
                    270
                ],
                [
                    897,
                    264
                ],
                [
                    904,
                    260
                ],
                [
                    886,
                    252
                ],
                [
                    872,
                    255
                ],
                [
                    866,
                    256
                ],
                [
                    856,
                    257
                ],
                [
                    847,
                    255
                ],
                [
                    848,
                    263
                ]
            ]
        },
        {
            "label": "motorcycble",
            "polygon": [
                [
                    988,
                    265
                ],
                [
                    998,
                    289
                ],
                [
                    1007,
                    289
                ],
                [
                    1007,
                    262
                ],
                [
                    999,
                    255
                ],
                [
                    982,
                    260
                ]
            ]
        },
        {
            "label": "motorcycble",
            "polygon": [
                [
                    1024,
                    262
                ],
                [
                    1023,
                    287
                ],
                [
                    1025,
                    286
                ],
                [
                    1027,
                    292
                ],
                [
                    1032,
                    289
                ],
                [
                    1031,
                    284
                ],
                [
                    1038,
                    278
                ],
                [
                    1040,
                    263
                ],
                [
                    1038,
                    257
                ],
                [
                    1033,
                    257
                ]
            ]
        },
        {
            "label": "motorcycble",
            "polygon": [
                [
                    1462,
                    301
                ],
                [
                    1488,
                    311
                ],
                [
                    1621,
                    317
                ],
                [
                    1620,
                    295
                ],
                [
                    1613,
                    284
                ],
                [
                    1521,
                    285
                ],
                [
                    1473,
                    281
                ]
            ]
        },
        {
            "label": "road",
            "polygon": [
                [
                    11,
                    320
                ],
                [
                    817,
                    285
                ],
                [
                    1914,
                    332
                ],
                [
                    1919,
                    746
                ],
                [
                    1919,
                    839
                ],
                [
                    0,
                    836
                ],
                [
                    0,
                    326
                ]
            ]
        },
        {
            "label": "cone",
            "polygon": [
                [
                    635,
                    529
                ],
                [
                    624,
                    617
                ],
                [
                    611,
                    625
                ],
                [
                    611,
                    655
                ],
                [
                    698,
                    657
                ],
                [
                    700,
                    626
                ],
                [
                    681,
                    622
                ],
                [
                    660,
                    532
                ]
            ]
        },
        {
            "label": "cone",
            "polygon": [
                [
                    1174,
                    423
                ],
                [
                    1167,
                    469
                ],
                [
                    1150,
                    472
                ],
                [
                    1168,
                    487
                ],
                [
                    1204,
                    482
                ],
                [
                    1185,
                    465
                ],
                [
                    1192,
                    426
                ]
            ]
        },
        {
            "label": "cone",
            "polygon": [
                [
                    1422,
                    379
                ],
                [
                    1407,
                    417
                ],
                [
                    1434,
                    416
                ]
            ]
        },
        {
            "label": "cone",
            "polygon": [
                [
                    1525,
                    357
                ],
                [
                    1517,
                    385
                ],
                [
                    1540,
                    386
                ]
            ]
        },
        {
            "label": "cone",
            "polygon": [
                [
                    1654,
                    350
                ],
                [
                    1648,
                    372
                ],
                [
                    1662,
                    372
                ]
            ]
        },
        {
            "label": "cone",
            "polygon": [
                [
                    1730,
                    345
                ],
                [
                    1724,
                    362
                ],
                [
                    1740,
                    367
                ]
            ]
        },
        {
            "label": "cone",
            "polygon": [
                [
                    1885,
                    346
                ],
                [
                    1875,
                    365
                ],
                [
                    1888,
                    363
                ]
            ]
        }
    ]
}